awslabs/documentdb_migration_mcp_server/__init__.py
awslabs/documentdb_migration_mcp_server/boundary_tools.py
awslabs/documentdb_migration_mcp_server/cdc_tools.py
awslabs/documentdb_migration_mcp_server/dms_buddy_tools.py
awslabs/documentdb_migration_mcp_server/full_load_tools.py
awslabs/documentdb_migration_mcp_server/index_tools.py
awslabs/documentdb_migration_mcp_server/migration_workflow.py
awslabs/documentdb_migration_mcp_server/server.py
awslabs/documentdb_migration_mcp_server/scripts/cdc-multiprocess.py
awslabs/documentdb_migration_mcp_server/scripts/dms_buddy.cfn
awslabs/documentdb_migration_mcp_server/scripts/dms_buddy.py
awslabs/documentdb_migration_mcp_server/scripts/documentdb_index_tool.py
awslabs/documentdb_migration_mcp_server/scripts/fl-multiprocess-filtered.py
awslabs/documentdb_migration_mcp_server/scripts/fl-multiprocess.py
documentdb_migration_mcp_server-0.7.0.dist-info/METADATA
documentdb_migration_mcp_server-0.7.0.dist-info/WHEEL
documentdb_migration_mcp_server-0.7.0.dist-info/entry_points.txt
documentdb_migration_mcp_server-0.7.0.dist-info/top_level.txt
documentdb_migration_mcp_server-0.7.0.dist-info/RECORD
