Metadata-Version: 2.4
Name: documentdb-migration-mcp-server
Version: 0.7.0
Summary: DocumentDB Migration MCP Server for migrating data to DocumentDB
Home-page: https://github.com/documentdb/documentdb-tools
Author: DocumentDB Team
Author-email: DocumentDB Team <documentdb-dev@example.com>
License: Apache-2.0
Project-URL: Homepage, https://github.com/documentdb/documentdb-tools
Project-URL: Documentation, https://github.com/documentdb/documentdb-tools
Project-URL: Repository, https://github.com/documentdb/documentdb-tools
Classifier: Development Status :: 4 - Beta
Classifier: Intended Audience :: Developers
Classifier: License :: OSI Approved :: Apache Software License
Classifier: Programming Language :: Python :: 3
Classifier: Programming Language :: Python :: 3.10
Classifier: Programming Language :: Python :: 3.11
Requires-Python: >=3.11
Requires-Dist: pydantic>=2.0.0
Requires-Dist: loguru>=0.6.0
Requires-Dist: pymongo>=4.0.0
Requires-Dist: boto3>=1.26.0
Requires-Dist: mcp-server>=0.1.0
Requires-Dist: humanize>=4.0.0
Dynamic: author
Dynamic: home-page
Dynamic: requires-python
